biopylib/__init__.py
biopylib/blast.py
biopylib/read_sequence.py
biopylib/sequence.py
biopylib/sequence_alignment.py
biopylib-0.0.5.dist-info/LICENSE
biopylib-0.0.5.dist-info/METADATA
biopylib-0.0.5.dist-info/WHEEL
biopylib-0.0.5.dist-info/top_level.txt
biopylib-0.0.5.dist-info/RECORD
