Metadata-Version: 2.1
Name: biopylib
Version: 0.0.5
Summary: Simplify the biological analysis
Home-page: https://github.com/shtrausslearning/biopylab
Author: Andrey Shtrauss
Author-email: shtraussart@gmail.com
License: UNKNOWN
Project-URL: Bug Tracker, https://github.com/shtrausslearning/biopylab/issues
Platform: UNKNOWN
Classifier: Programming Language :: Python :: 3
Classifier: License :: OSI Approved :: MIT License
Classifier: Operating System :: OS Independent
Requires-Python: >=3.6
License-File: LICENSE
